Workbook

Sheet Ventas_raw_200
A1: ID_Transaccion | B1: Fecha | C1: Sucursal | D1: Vendedor | E1: Producto | F1: Cantidad | G1: Precio_Unitario | H1: Costo_Unitario
A2: TRX-1001 | B2: 46111 | C2: Corrientes | D2: Ana Martinez | E2: mates de madera calada | F2: 8 | G2: 8500 | H2: 4800
A3: TRX-1002 | B3: 46106 | C3: Posadas | D3: Juan Perez | E3: termo acero inoxidable 1.3l | F3: 2 | G3: 32000 | H3: 21000
A4: TRX-1003 | B4: 46082 | C4: Posadas | D4: Juan Perez | E4: Mouse Inalámbrico Ergonómico | F4: 23 | G4: 15000 | H4: 9500
A5: TRX-1004 | B5: 46107 | C5: Resistencia | D5: ANA MARTINEZ | E5: Yerba Mate Premium 1kg | F5: 25 | G5: 3800 | H5: 2500
A6: TRX-1005 | B6: 46102 | C6: CORRIENTES | D6: ANA MARTINEZ | E6: Mouse Inalámbrico Ergonómico | F6: 3 | G6: 15000 | H6: 9500
A7: TRX-1006 | B7: 46051 | C7: Formosa | D7: Juan Perez | E7: correa reforzada canina 3m | F7: 18 | G7: 9200 | H7: 5500
A8: TRX-1007 | B8: 46025 | C8: Resistencia | D8: ANA MARTINEZ | E8: Alimento Perro Adulto 15kg | F8: 12 | G8: 35000 | H8: 24000
A9: TRX-1008 | B9: 46050 | C9: Formosa | D9: MARIA GOMEZ | E9: Alimento Gato Castrado 10kg | F9: 8 | G9: 29500 | H9: 20000
A10: TRX-1009 | B10: 46111 | C10: Resistencia | D10: juan perez | E10: Cargador Rápido USB-C 65W | F10: 7 | G10: 22000 | H10: 14000
A11: TRX-1010 | B11: 46076 | C11: Posadas | D11: Ana Martinez | E11: Snack Premios Perro 250g | F11: 24 | G11: 3100 | H11: 1800
A12: TRX-1011 | B12: 46024 | C12: POSADAS | D12: Ana Martinez | E12: Alimento Gato Castrado 10kg | F12: 22 | G12: 29500 | H12: 20000
A13: TRX-1012 | B13: 46099 | C13: Corrientes | D13: ANA MARTINEZ | E13: termo acero inoxidable 1.3l | F13: 9 | G13: 32000 | H13: 21000
... A201: TRX-1200 | B201: 46075 | C201: Corrientes | D201: Carlos Ruiz | E201: Mates de Madera Calada | F201: 10 | G201: 8500 | H201: 4800

Sheet Maestro_productos_15
A1: SKU | B1: Producto | C1: Categoria | D1: Proveedor | E1: Precio_Lista | F1: Costo_Base
A2: SKU-101 | B2: Yerba Mate Premium 1kg | C2: Alimentos | D2: Cooperativa Neike | E2: 3800 | F2: 2500
A3: SKU-102 | B3: Alimento Perro Adulto 15kg | C3: Mascotas | D3: NutriDog Arg | E3: 35000 | F3: 24000
A4: SKU-103 | B4: Auriculares Bluetooth Pro | C4: Tecnología | D4: TechImport S.R.L. | E4: 28000 | F4: 18000
A5: SKU-104 | B5: Soporte Regulable Notebook | C5: Tecnología | D5: TechImport S.R.L. | E5: 19500 | F5: 12000
A6: SKU-105 | B6: Correa Reforzada Canina 3m | C6: Mascotas | D6: PetStyle Litoral | E6: 9200 | F6: 5500
A7: SKU-106 | B7: Juguete Mordillo Goma | C7: Mascotas | D7: PetStyle Litoral | E7: 4800 | F7: 2700
A8: SKU-107 | B8: Alimento Gato Castrado 10kg | C8: Mascotas | D8: NutriDog Arg | E8: 29500 | F8: 20000
A9: SKU-108 | B9: Teclado Mecánico RGB | C9: Tecnología | D9: TechImport S.R.L. | E9: 45000 | F9: 30000
A10: SKU-109 | B10: Café en Grano Intenso 1kg | C10: Alimentos | D10: Distribuidora del Nordeste | E10: 18500 | F10: 12500
A11: SKU-110 | B11: Mates de Madera Calada | C11: Bazar | D11: Artesanías Guaraníes | E11: 8500 | F11: 4800
A12: SKU-111 | B12: Termo Acero Inoxidable 1.3L | C12: Bazar | D12: Distribuidora del Nordeste | E12: 32000 | F12: 21000
... A16: SKU-115 | B16: Cargador Rápido USB-C 65W | C16: Tecnología | D16: TechImport S.R.L. | E16: 22000 | F16: 14000

Sheet Tabla_Solucion
A1: ID_Transaccion | B1: Largo_ID | C1: Fecha | D1: Sucursal | E1: Vendedor | F1: Producto | G1: Cantidad | H1: Precio_Unitario | I1: Costo_Unitario | J1: Sucursal_Limpia | K1: Cantidad_Auditada | L1: Vendedor_Limpio | M1: Producto_Limpio | N1: Proveedor_oficial | O1: Categoria_oficial | P1: Total_Venta | Q1: Total_Costo | R1: Ganancia_Neta | S1: Comision
A2: TRX-1001 | B2: =LEN(A2) -> 8 | C2: 46111 | D2: Corrientes | E2: Ana Martinez | F2: mates de madera calada | G2: 8 | H2: 8500 | I2: 4800 | J2: =TRIM(PROPER(D2) ) -> Corrientes | K2: =IF(G2<=0,1,G2) -> 8 | L2: =PROPER(E2) -> Ana Martinez | M2: =PROPER(F2) -> Mates De Madera Calada | N2: {=IFERROR(_xlfn.XLOOKUP(M2, Maestro_productos_15!$B:$B, Maestro_productos_15!$D:$D), "No encontrado")} -> Artesanías Guaraníes | O2: {=IFERROR(_xlfn.XLOOKUP(M2,Maestro_productos_15!$B:$B,Maestro_productos_15!$C:$C), "Sin Categoria")} -> Bazar | P2: =H2*G2 -> 68000 | Q2: =I2*G2 -> 38400 | R2: =P2-Q2 -> 29600 | S2: =IFS(AND(H2>25000, J2="Corrientes"),K2*H2*0.06, H2>25000,K2*H2*0.04, TRUE, K2*H2*0.02) -> 1360
A3: TRX-1002 | B3: =LEN(A3) -> 8 | C3: 46106 | D3: Posadas | E3: Juan Perez | F3: termo acero inoxidable 1.3l | G3: 2 | H3: 32000 | I3: 21000 | J3: =TRIM(PROPER(D3) ) -> Posadas | K3: =IF(G3<=0,1,G3) -> 2 | L3: =PROPER(E3) -> Juan Perez | M3: =PROPER(F3) -> Termo Acero Inoxidable 1.3L | N3: {=IFERROR(_xlfn.XLOOKUP(M3, Maestro_productos_15!$B:$B, Maestro_productos_15!$D:$D), "No encontrado")} -> Distribuidora del Nordeste | O3: {=IFERROR(_xlfn.XLOOKUP(M3,Maestro_productos_15!$B:$B,Maestro_productos_15!$C:$C), "Sin Categoria")} -> Bazar | P3: =H3*G3 -> 64000 | Q3: =I3*G3 -> 42000 | R3: =P3-Q3 -> 22000 | S3: =IFS(AND(H3>25000, J3="Corrientes"),K3*H3*0.06, H3>25000,K3*H3*0.04, TRUE, K3*H3*0.02) -> 2560
A4: TRX-1003 | B4: =LEN(A4) -> 8 | C4: 46082 | D4: Posadas | E4: Juan Perez | F4: Mouse Inalámbrico Ergonómico | G4: 23 | H4: 15000 | I4: 9500 | J4: =TRIM(PROPER(D4) ) -> Posadas | K4: =IF(G4<=0,1,G4) -> 23 | L4: =PROPER(E4) -> Juan Perez | M4: =PROPER(F4) -> Mouse Inalámbrico Ergonómico | N4: {=IFERROR(_xlfn.XLOOKUP(M4, Maestro_productos_15!$B:$B, Maestro_productos_15!$D:$D), "No encontrado")} -> TechImport S.R.L. | O4: {=IFERROR(_xlfn.XLOOKUP(M4,Maestro_productos_15!$B:$B,Maestro_productos_15!$C:$C), "Sin Categoria")} -> Tecnología | P4: =H4*G4 -> 345000 | Q4: =I4*G4 -> 218500 | R4: =P4-Q4 -> 126500 | S4: =IFS(AND(H4>25000, J4="Corrientes"),K4*H4*0.06, H4>25000,K4*H4*0.04, TRUE, K4*H4*0.02) -> 6900
A5: TRX-1004 | B5: =LEN(A5) -> 8 | C5: 46107 | D5: Resistencia | E5: ANA MARTINEZ | F5: Yerba Mate Premium 1kg | G5: 25 | H5: 3800 | I5: 2500 | J5: =TRIM(PROPER(D5) ) -> Resistencia | K5: =IF(G5<=0,1,G5) -> 25 | L5: =PROPER(E5) -> Ana Martinez | M5: =PROPER(F5) -> Yerba Mate Premium 1Kg | N5: {=IFERROR(_xlfn.XLOOKUP(M5, Maestro_productos_15!$B:$B, Maestro_productos_15!$D:$D), "No encontrado")} -> Cooperativa Neike | O5: {=IFERROR(_xlfn.XLOOKUP(M5,Maestro_productos_15!$B:$B,Maestro_productos_15!$C:$C), "Sin Categoria")} -> Alimentos | P5: =H5*G5 -> 95000 | Q5: =I5*G5 -> 62500 | R5: =P5-Q5 -> 32500 | S5: =IFS(AND(H5>25000, J5="Corrientes"),K5*H5*0.06, H5>25000,K5*H5*0.04, TRUE, K5*H5*0.02) -> 1900
A6: TRX-1005 | B6: =LEN(A6) -> 8 | C6: 46102 | D6: CORRIENTES | E6: ANA MARTINEZ | F6: Mouse Inalámbrico Ergonómico | G6: 3 | H6: 15000 | I6: 9500 | J6: =TRIM(PROPER(D6) ) -> Corrientes | K6: =IF(G6<=0,1,G6) -> 3 | L6: =PROPER(E6) -> Ana Martinez | M6: =PROPER(F6) -> Mouse Inalámbrico Ergonómico | N6: {=IFERROR(_xlfn.XLOOKUP(M6, Maestro_productos_15!$B:$B, Maestro_productos_15!$D:$D), "No encontrado")} -> TechImport S.R.L. | O6: {=IFERROR(_xlfn.XLOOKUP(M6,Maestro_productos_15!$B:$B,Maestro_productos_15!$C:$C), "Sin Categoria")} -> Tecnología | P6: =H6*G6 -> 45000 | Q6: =I6*G6 -> 28500 | R6: =P6-Q6 -> 16500 | S6: =IFS(AND(H6>25000, J6="Corrientes"),K6*H6*0.06, H6>25000,K6*H6*0.04, TRUE, K6*H6*0.02) -> 900
A7: TRX-1006 | B7: =LEN(A7) -> 8 | C7: 46051 | D7: Formosa | E7: Juan Perez | F7: correa reforzada canina 3m | G7: 18 | H7: 9200 | I7: 5500 | J7: =TRIM(PROPER(D7) ) -> Formosa | K7: =IF(G7<=0,1,G7) -> 18 | L7: =PROPER(E7) -> Juan Perez | M7: =PROPER(F7) -> Correa Reforzada Canina 3M | N7: {=IFERROR(_xlfn.XLOOKUP(M7, Maestro_productos_15!$B:$B, Maestro_productos_15!$D:$D), "No encontrado")} -> PetStyle Litoral | O7: {=IFERROR(_xlfn.XLOOKUP(M7,Maestro_productos_15!$B:$B,Maestro_productos_15!$C:$C), "Sin Categoria")} -> Mascotas | P7: =H7*G7 -> 165600 | Q7: =I7*G7 -> 99000 | R7: =P7-Q7 -> 66600 | S7: =IFS(AND(H7>25000, J7="Corrientes"),K7*H7*0.06, H7>25000,K7*H7*0.04, TRUE, K7*H7*0.02) -> 3312
A8: TRX-1007 | B8: =LEN(A8) -> 8 | C8: 46025 | D8: Resistencia | E8: ANA MARTINEZ | F8: Alimento Perro Adulto 15kg | G8: 12 | H8: 35000 | I8: 24000 | J8: =TRIM(PROPER(D8) ) -> Resistencia | K8: =IF(G8<=0,1,G8) -> 12 | L8: =PROPER(E8) -> Ana Martinez | M8: =PROPER(F8) -> Alimento Perro Adulto 15Kg | N8: {=IFERROR(_xlfn.XLOOKUP(M8, Maestro_productos_15!$B:$B, Maestro_productos_15!$D:$D), "No encontrado")} -> NutriDog Arg | O8: {=IFERROR(_xlfn.XLOOKUP(M8,Maestro_productos_15!$B:$B,Maestro_productos_15!$C:$C), "Sin Categoria")} -> Mascotas | P8: =H8*G8 -> 420000 | Q8: =I8*G8 -> 288000 | R8: =P8-Q8 -> 132000 | S8: =IFS(AND(H8>25000, J8="Corrientes"),K8*H8*0.06, H8>25000,K8*H8*0.04, TRUE, K8*H8*0.02) -> 16800
A9: TRX-1008 | B9: =LEN(A9) -> 8 | C9: 46050 | D9: Formosa | E9: MARIA GOMEZ | F9: Alimento Gato Castrado 10kg | G9: 8 | H9: 29500 | I9: 20000 | J9: =TRIM(PROPER(D9) ) -> Formosa | K9: =IF(G9<=0,1,G9) -> 8 | L9: =PROPER(E9) -> Maria Gomez | M9: =PROPER(F9) -> Alimento Gato Castrado 10Kg | N9: {=IFERROR(_xlfn.XLOOKUP(M9, Maestro_productos_15!$B:$B, Maestro_productos_15!$D:$D), "No encontrado")} -> NutriDog Arg | O9: {=IFERROR(_xlfn.XLOOKUP(M9,Maestro_productos_15!$B:$B,Maestro_productos_15!$C:$C), "Sin Categoria")} -> Mascotas | P9: =H9*G9 -> 236000 | Q9: =I9*G9 -> 160000 | R9: =P9-Q9 -> 76000 | S9: =IFS(AND(H9>25000, J9="Corrientes"),K9*H9*0.06, H9>25000,K9*H9*0.04, TRUE, K9*H9*0.02) -> 9440
A10: TRX-1009 | B10: =LEN(A10) -> 8 | C10: 46111 | D10: Resistencia | E10: juan perez | F10: Cargador Rápido USB-C 65W | G10: 7 | H10: 22000 | I10: 14000 | J10: =TRIM(PROPER(D10) ) -> Resistencia | K10: =IF(G10<=0,1,G10) -> 7 | L10: =PROPER(E10) -> Juan Perez | M10: =PROPER(F10) -> Cargador Rápido Usb-C 65W | N10: {=IFERROR(_xlfn.XLOOKUP(M10, Maestro_productos_15!$B:$B, Maestro_productos_15!$D:$D), "No encontrado")} -> TechImport S.R.L. | O10: {=IFERROR(_xlfn.XLOOKUP(M10,Maestro_productos_15!$B:$B,Maestro_productos_15!$C:$C), "Sin Categoria")} -> Tecnología | P10: =H10*G10 -> 154000 | Q10: =I10*G10 -> 98000 | R10: =P10-Q10 -> 56000 | S10: =IFS(AND(H10>25000, J10="Corrientes"),K10*H10*0.06, H10>25000,K10*H10*0.04, TRUE, K10*H10*0.02) -> 3080
A11: TRX-1010 | B11: =LEN(A11) -> 8 | C11: 46076 | D11: Posadas | E11: Ana Martinez | F11: Snack Premios Perro 250g | G11: 24 | H11: 3100 | I11: 1800 | J11: =TRIM(PROPER(D11) ) -> Posadas | K11: =IF(G11<=0,1,G11) -> 24 | L11: =PROPER(E11) -> Ana Martinez | M11: =PROPER(F11) -> Snack Premios Perro 250G | N11: {=IFERROR(_xlfn.XLOOKUP(M11, Maestro_productos_15!$B:$B, Maestro_productos_15!$D:$D), "No encontrado")} -> NutriDog Arg | O11: {=IFERROR(_xlfn.XLOOKUP(M11,Maestro_productos_15!$B:$B,Maestro_productos_15!$C:$C), "Sin Categoria")} -> Mascotas | P11: =H11*G11 -> 74400 | Q11: =I11*G11 -> 43200 | R11: =P11-Q11 -> 31200 | S11: =IFS(AND(H11>25000, J11="Corrientes"),K11*H11*0.06, H11>25000,K11*H11*0.04, TRUE, K11*H11*0.02) -> 1488
A12: TRX-1011 | B12: =LEN(A12) -> 8 | C12: 46024 | D12: POSADAS | E12: Ana Martinez | F12: Alimento Gato Castrado 10kg | G12: 22 | H12: 29500 | I12: 20000 | J12: =TRIM(PROPER(D12) ) -> Posadas | K12: =IF(G12<=0,1,G12) -> 22 | L12: =PROPER(E12) -> Ana Martinez | M12: =PROPER(F12) -> Alimento Gato Castrado 10Kg | N12: {=IFERROR(_xlfn.XLOOKUP(M12, Maestro_productos_15!$B:$B, Maestro_productos_15!$D:$D), "No encontrado")} -> NutriDog Arg | O12: {=IFERROR(_xlfn.XLOOKUP(M12,Maestro_productos_15!$B:$B,Maestro_productos_15!$C:$C), "Sin Categoria")} -> Mascotas | P12: =H12*G12 -> 649000 | Q12: =I12*G12 -> 440000 | R12: =P12-Q12 -> 209000 | S12: =IFS(AND(H12>25000, J12="Corrientes"),K12*H12*0.06, H12>25000,K12*H12*0.04, TRUE, K12*H12*0.02) -> 25960
A13: TRX-1012 | B13: =LEN(A13) -> 8 | C13: 46099 | D13: Corrientes | E13: ANA MARTINEZ | F13: termo acero inoxidable 1.3l | G13: 9 | H13: 32000 | I13: 21000 | J13: =TRIM(PROPER(D13) ) -> Corrientes | K13: =IF(G13<=0,1,G13) -> 9 | L13: =PROPER(E13) -> Ana Martinez | M13: =PROPER(F13) -> Termo Acero Inoxidable 1.3L | N13: {=IFERROR(_xlfn.XLOOKUP(M13, Maestro_productos_15!$B:$B, Maestro_productos_15!$D:$D), "No encontrado")} -> Distribuidora del Nordeste | O13: {=IFERROR(_xlfn.XLOOKUP(M13,Maestro_productos_15!$B:$B,Maestro_productos_15!$C:$C), "Sin Categoria")} -> Bazar | P13: =H13*G13 -> 288000 | Q13: =I13*G13 -> 189000 | R13: =P13-Q13 -> 99000 | S13: =IFS(AND(H13>25000, J13="Corrientes"),K13*H13*0.06, H13>25000,K13*H13*0.04, TRUE, K13*H13*0.02) -> 17280
... A201: TRX-1200 | B201: =LEN(A201) -> 8 | C201: 46075 | D201: Corrientes | E201: Carlos Ruiz | F201: Mates de Madera Calada | G201: 10 | H201: 8500 | I201: 4800 | J201: =TRIM(PROPER(D201) ) -> Corrientes | K201: =IF(G201<=0,1,G201) -> 10 | L201: =PROPER(E201) -> Carlos Ruiz | M201: =PROPER(F201) -> Mates De Madera Calada | N201: {=IFERROR(_xlfn.XLOOKUP(M201, Maestro_productos_15!$B:$B, Maestro_productos_15!$D:$D), "No encontrado")} -> Artesanías Guaraníes | O201: {=IFERROR(_xlfn.XLOOKUP(M201,Maestro_productos_15!$B:$B,Maestro_productos_15!$C:$C), "Sin Categoria")} -> Bazar | P201: =H201*G201 -> 85000 | Q201: =I201*G201 -> 48000 | R201: =P201-Q201 -> 37000 | S201: =IFS(AND(H201>25000, J201="Corrientes"),K201*H201*0.06, H201>25000,K201*H201*0.04, TRUE, K201*H201*0.02) -> 1700

Sheet Reporte_Consolidado
A1: CIUDAD | B1: TOTAL_VENTAS
A2: Corrientes | B2: {=SUM( IFS(Tabla_1[Sucursal_Limpia]=A2,Tabla_1[Cantidad_Auditada]*Tabla_1[Precio_Unitario], TRUE, 0 ))} -> 8339700
A3: Posadas | B3: {=SUM( IFS(Tabla_Solucion!$J$2:$J$201=A3,Tabla_Solucion!$K$2:$K$201*Tabla_Solucion!$H$2:$H$201, TRUE, 0 ))} -> 12305400
A4: Resistencia | B4: {=SUM( IFS(Tabla_Solucion!$J$2:$J$201=A4,Tabla_Solucion!$K$2:$K$201*Tabla_Solucion!$H$2:$H$201, TRUE, 0 ))} -> 13394400
A5: Formosa | B5: {=SUM( IFS(Tabla_Solucion!$J$2:$J$201=A5,Tabla_Solucion!$K$2:$K$201*Tabla_Solucion!$H$2:$H$201, TRUE, 0 ))} -> 6499100

Sheet Dashoboard_Ejecutivo
H2: GANANCIA NETA TOTAL | I2: =SUM(Tabla_1[Ganancia_Neta]) -> 14127200
H3: MARGEN PROMEDIO GENERAL | I3: =AVERAGE(Tabla_1[Ganancia_Neta]) / AVERAGE(Tabla_1[Total_Venta]) -> 0.35092879
